model_contrast/__init__.py
model_contrast/classification_contrast.py
model_contrast/regression_contrast.py
test/__init__.py
test/test_binary_classification.py
test/test_multiclass_classification.py
test/test_regression.py
model_contrast-0.1.8.dist-info/LICENSE
model_contrast-0.1.8.dist-info/METADATA
model_contrast-0.1.8.dist-info/WHEEL
model_contrast-0.1.8.dist-info/top_level.txt
model_contrast-0.1.8.dist-info/RECORD
