Metadata-Version: 2.1
Name: model-contrast
Version: 0.1.8
Summary: Compare two ML models.
Home-page: https://github.com/ArmandDS/model_contrast
Author: Armand Olivares
Author-email: armandds@users.noreply.github.com
License: MIT
Platform: UNKNOWN
Requires-Dist: numpy (>=1.19.0)
Requires-Dist: pandas (>=1.1.5)
Requires-Dist: scipy (>=1.4.1)
Requires-Dist: scikit-learn (>=0.22.2)
Requires-Dist: statsmodels
